obsidiantools/__init__.py
obsidiantools/_constants.py
obsidiantools/_io.py
obsidiantools/api.py
obsidiantools/canvas_utils.py
obsidiantools/html_processing.py
obsidiantools/md_utils.py
obsidiantools/media_utils.py
obsidiantools-0.10.0.dist-info/LICENSE
obsidiantools-0.10.0.dist-info/METADATA
obsidiantools-0.10.0.dist-info/WHEEL
obsidiantools-0.10.0.dist-info/top_level.txt
obsidiantools-0.10.0.dist-info/RECORD
