Metadata-Version: 2.1
Name: obsidiantools
Version: 0.10.0
Summary: Obsidian Tools - a Python interface for Obsidian.md vaults
Home-page: https://github.com/mfarragher/obsidiantools
Author: Mark Farragher
License: BSD
Project-URL: Source, https://github.com/mfarragher/obsidiantools
Keywords: obsidian,obsidian.md,knowledge,note-taking,notes,knowledge management,connected notes
Classifier: Development Status :: 3 - Alpha
Classifier: Intended Audience :: Education
Classifier: Intended Audience :: Science/Research
Classifier: Topic :: Text Processing :: Markup :: Markdown
Classifier: Topic :: Office/Business
Classifier: Topic :: Education
Classifier: Programming Language :: Python :: 3.11
Classifier: Programming Language :: Python :: 3.10
Classifier: Programming Language :: Python :: 3.9
Classifier: License :: OSI Approved :: BSD License
Classifier: Operating System :: OS Independent
Requires-Python: >=3.9
License-File: LICENSE
Requires-Dist: markdown
Requires-Dist: pymdown-extensions
Requires-Dist: html2text
Requires-Dist: pandas
Requires-Dist: numpy
Requires-Dist: networkx
Requires-Dist: python-frontmatter
Requires-Dist: beautifulsoup4
Requires-Dist: bleach
Requires-Dist: lxml
